[
  {
    "id": "exemple-risotto",
    "title": "Risotto aux Champignons",
    "category": "plat",
    "servings": 4,
    "ingredients": [
      "300g de riz arborio (ou carnaroli)",
      "400g de champignons de Paris (ou mélange de champignons)",
      "1 oignon",
      "2 gousses d'ail",
      "1L de bouillon de légumes (chaud)",
      "100ml de vin blanc sec",
      "50g de parmesan râpé",
      "50g de beurre",
      "3 cuillères à soupe d'huile d'olive",
      "Persil frais",
      "Sel et poivre"
    ]
  },
  {
    "id": "exemple-tarte-aux-pommes",
    "title": "Tarte aux Pommes Classique",
    "category": "dessert",
    "servings": 4,
    "ingredients": [
      "250g de farine",
      "125g de beurre froid",
      "1 pincée de sel",
      "3-4 cuillères à soupe d'eau froide"
    ]
  }
]